<xml xmlns:o="urn:schemas-microsoft-com:office:office">
 <o:MainFile HRef="../Program%202.html"/>
 <o:File HRef="program%20latihan%20diaplikasi%203_31416_image001.png"
  PublicationID="program latihan diaplikasi 3_31416"/>
 <o:File HRef="program%20latihan%20diaplikasi%203_31416_image002.png"
  PublicationID="program latihan diaplikasi 3_31416"/>
 <o:File HRef="program%20latihan%20diaplikasi%203_31416_image003.png"
  PublicationID="program latihan diaplikasi 3_31416"/>
 <o:File HRef="program%20latihan%20diaplikasi%203_31416_image004.png"
  PublicationID="program latihan diaplikasi 3_31416"/>
 <o:File HRef="program%20latihan%20diaplikasi%203_31416_image005.png"
  PublicationID="program latihan diaplikasi 3_31416"/>
 <o:File HRef="program%20latihan%20diaplikasi%203_31416_image006.png"
  PublicationID="program latihan diaplikasi 3_31416"/>
 <o:File HRef="program%20latihan%20diaplikasi%203_31416_image007.png"
  PublicationID="program latihan diaplikasi 3_31416"/>
 <o:File HRef="program%20latihan%20diaplikasi%203_31416_image008.png"
  PublicationID="program latihan diaplikasi 3_31416"/>
 <o:File HRef="program%20latihan%20diaplikasi%203_31416_image009.gif"
  PublicationID="program latihan diaplikasi 3_31416"/>
 <o:File HRef="program%20latihan%20diaplikasi%203_31416_image010.png"
  PublicationID="program latihan diaplikasi 3_31416"/>
 <o:File HRef="program%20latihan%20diaplikasi%203_31416_image011.png"
  PublicationID="program latihan diaplikasi 3_31416"/>
 <o:File HRef="program%20latihan%20diaplikasi%203_31416_image012.png"
  PublicationID="program latihan diaplikasi 3_31416"/>
 <o:File HRef="program%20latihan%20diaplikasi%203_31416_image013.gif"
  PublicationID="program latihan diaplikasi 3_31416"/>
 <o:File HRef="program%20latihan%20diaplikasi%203_31416_image014.png"
  PublicationID="program latihan diaplikasi 3_31416"/>
 <o:File HRef="program%20latihan%20diaplikasi%203_31416_image015.png"
  PublicationID="program latihan diaplikasi 3_31416"/>
 <o:File HRef="program%20latihan%20diaplikasi%203_31416_image016.gif"
  PublicationID="program latihan diaplikasi 3_31416"/>
 <o:File HRef="program%20latihan%20diaplikasi%203_31416_image017.png"
  PublicationID="program latihan diaplikasi 3_31416"/>
 <o:File HRef="program%20latihan%20diaplikasi%203_31416_image018.png"
  PublicationID="program latihan diaplikasi 3_31416"/>
 <o:File HRef="program%20latihan%20diaplikasi%203_31416_image019.png"
  PublicationID="program latihan diaplikasi 3_31416"/>
 <o:File HRef="program%20latihan%20diaplikasi%203_31416_image020.png"
  PublicationID="program latihan diaplikasi 3_31416"/>
 <o:File HRef="program%20latihan%20diaplikasi%203_31416_image021.png"
  PublicationID="program latihan diaplikasi 3_31416"/>
 <o:File HRef="program%20latihan%20diaplikasi%203_31416_image022.png"
  PublicationID="program latihan diaplikasi 3_31416"/>
 <o:File HRef="program%20latihan%20diaplikasi%203_31416_image023.png"
  PublicationID="program latihan diaplikasi 3_31416"/>
 <o:File HRef="program%20latihan%20diaplikasi%203_31416_image024.png"
  PublicationID="program latihan diaplikasi 3_31416"/>
 <o:File HRef="program%20latihan%20diaplikasi%203_31416_image025.png"
  PublicationID="program latihan diaplikasi 3_31416"/>
 <o:File HRef="program%20latihan%20diaplikasi%203_31416_image026.png"
  PublicationID="program latihan diaplikasi 3_31416"/>
 <o:File HRef="program%20latihan%20diaplikasi%203_31416_image027.gif"
  PublicationID="program latihan diaplikasi 3_31416"/>
 <o:File HRef="filelist.xml"/>
</xml>